mongoex/__init__.py
mongoex/__version__.py
mongoex/builder/__init__.py
mongoex/builder/pipeline.py
mongoex/core/__init__.py
mongoex/core/expressions.py
mongoex/core/fields.py
mongoex/models/__init__.py
mongoex/models/introspection.py
mongoex/operators/__init__.py
mongoex/operators/aggregation.py
mongoex/operators/array.py
mongoex/operators/comparison.py
mongoex/operators/field.py
mongoex/operators/logical.py
mongoex/utils/__init__.py
mongoex/utils/json_to_mongoex.py
mongoex/utils/testing_utils.py
mongoex/validation/__init__.py
mongoex/validation/field_validator.py
mongoex-0.0.1.dist-info/licenses/LICENSE
mongoex-0.0.1.dist-info/METADATA
mongoex-0.0.1.dist-info/WHEEL
mongoex-0.0.1.dist-info/top_level.txt
mongoex-0.0.1.dist-info/RECORD
