Metadata-Version: 2.4
Name: mongoex
Version: 0.0.1
Summary: MongoDB query building using Python's AST module with type-safe fluent APIs
Author-email: Eric Miguel <eric.mrib@gmail.com>
Maintainer-email: Eric Miguel <eric.mrib@gmail.com>
License:                     GNU AFFERO GENERAL PUBLIC LICENSE
Project-URL: Homepage, https://github.com/ericmiguel/mongoex
Project-URL: Repository, https://github.com/ericmiguel/mongoex
Project-URL: Issues, https://github.com/ericmiguel/mongoex/issues
Project-URL: Changelog, https://github.com/ericmiguel/mongoex/blob/main/CHANGELOG.md
Keywords: mongodb,query-builder,type-safe,aggregation,database,ast,fluent-api,pymongo
Classifier: Development Status :: 2 - Pre-Alpha
Classifier: Intended Audience :: Developers
Classifier: License :: OSI Approved :: GNU Affero General Public License v3
Classifier: Operating System :: OS Independent
Classifier: Programming Language :: Python :: 3
Classifier: Programming Language :: Python :: 3.12
Classifier: Programming Language :: Python :: 3.13
Classifier: Programming Language :: Python :: 3 :: Only
Classifier: Topic :: Database
Classifier: Topic :: Software Development :: Libraries :: Python Modules
Classifier: Topic :: Database :: Database Engines/Servers
Classifier: Typing :: Typed
Requires-Python: >=3.12
License-File: LICENSE
Requires-Dist: pydantic>=2.11.9
Requires-Dist: pymongo>=4.0
Dynamic: license-file
